{"cd":"01408","lastUpdate":"20260219132344502","unit":"2.0","delivery":{"mode":"onsite","raw":"対面のみ","isMedia":false},"eval":{"rows":[{"item":"小テスト","weight":25,"type":"quiz"},{"item":"学習意欲・授業参加度","weight":25,"type":"attendance"},{"item":"期末試験","weight":50,"type":"exam"}]},"summary":"目的は、ドイツ語で読み書き・会話・リスニング力を身に着けること。また、ドイツ語の文法を正しく理解し、活用する。","aims":"ドイツ語入門・自己紹介・家族紹介・買い物の会話・余暇活動について話す・大学での日常生活を描写する・食事と栄養について話す・職業と職種について話す・健康と病気について話す","goals":["自己紹介：人称代名詞・動詞の現在形・Ｗで始まる疑問代名詞","家族紹介：人称代名詞と動詞の現在形・冠詞と名詞の性","買い物の際の会話：１格と４格、Ja/Neinで答える疑問文・ja,nine,dochの答え方","余暇活動について話す：不規則動詞・所有冠詞","大学での日常生活を描写する：分離動詞と文構造・時間を表す前置詞","食事と栄養について話す：話法の助動詞・話法の助動詞と文構造","職業と職種について話す：３格と人称代名詞の３格・３格を取る前置詞","健康と病気について話す：指示、依頼、勧めの表現・話法の助動詞solle、manの用法"],"plan":[{"n":1,"text":"オリエンテーション・アルファベット・発音を学ぶ"},{"n":2,"text":"挨拶について学ぶ レッスン１/タスク１・２"},{"n":3,"text":"レッスン１/タスク３・４ 課題：レッスン１/タスク５"},{"n":4,"text":"レッスン１/タスク５～８"},{"n":5,"text":"小テスト：レッスン１ レッスン２/１～２"},{"n":6,"text":"レッスン２/タスク３"},{"n":7,"text":"レッスン２/タスク４～５"},{"n":8,"text":"レッスン２/タスク６～８"},{"n":9,"text":"小テスト：レッスン２ レッスン３/タスク１・２"},{"n":10,"text":"レッスン３/３～５ 課題：レッスン３/タスク７"},{"n":11,"text":"レッスン３/タスク６・７"},{"n":12,"text":"小テスト：レッスン３ レッスン４/タスク１・２"},{"n":13,"text":"レッスン４/タスク２～４"},{"n":14,"text":"レッスン４/タスク２～４/タスク４・５ 課題：レッスン４/タスク６"},{"n":15,"text":"レッスン４/タスク６・７"},{"n":16,"text":"小テスト：レッスン４ レッスン５/タスク１・２"},{"n":17,"text":"レッスン５/タスク２"},{"n":18,"text":"レッスン５/タスク２・３ 課題：レッスン５/タスク４"},{"n":19,"text":"レッスン５/タスク４～６"},{"n":20,"text":"小テスト：レッスン５ レッスン６/タスク１・２"},{"n":21,"text":"レッスン６/タスク２・３"},{"n":22,"text":"レッスン６/タスク４・５"},{"n":23,"text":"小テスト：レッスン６ レッスン７/タスク１・２"},{"n":24,"text":"レッスン７/タスク２・３ 課題：レッスン７/タスク４"},{"n":25,"text":"レッスン７/タスク４"},{"n":26,"text":"小テスト：レッスン７ レッスン８/タスク１・２"},{"n":27,"text":"レッスン８/タスク２・３"},{"n":28,"text":"レッスン８/タスク７"},{"n":29,"text":"小テスト：レッスン８ レッスン９/タスク１ 課題：レッスン９/タスク２"},{"n":30,"text":"レッスン９/タスク２・３"},{"n":31,"text":"期末テスト：レッスン１～９"},{"n":32,"text":"テスト返し"}],"textbooks":"教科書 Module１Ａ１ Ikumi Waragai/Andeas Meyer/Tatsuya Ohta著 朝日出版社 ２０２４年","prereq":"ドイツ語を学ぶ意欲がある人","prep":"予習・復習をしっかりする。","officeHour":[{"name":"アルブレヒト岡﨑グンヒルト","day":"火曜日","time":"12:00～12：30","place":"教室"}],"keywords":["ドイツ語入門"],"teachers":["◎ アルブレヒト 岡﨑 グンヒルト"],"numbering":["02-0520-21","04-0231-21"],"extra":[{"label":"英文科目名","text":"German I(In Liberal Arts and Science)"},{"label":"区分1","text":"平成20年度以降入学生／令和６年度以降入学生"},{"label":"区分2","text":"共通教育）教養科目外国語分野／国際コミュニケーション科目初修外国語・日本語"},{"label":"履修における注意点","text":"１外国語（ドイツ語）履修上限年間６単位"},{"label":"この授業で身につける「10+1の能力」","text":"専門分野に関する知識\n人類の文化・社会・自然に関する知識\n語学に関するリテラシー\nコミュニケーション力"},{"label":"履修に係わる注意事項\n【NOTES ON CLASS ENROLLMENT】","text":"人数は５０人まで"},{"label":"教員の実務経験の有無","text":"無"},{"label":"授業形態","text":"口頭での質疑やディスカッションを含む\n授業中や授業時間外のグループワークを含む"}]}