{"cd":"1A307","lastUpdate":"20260311195422198","unit":"2.0","delivery":{"mode":"hybrid","raw":"主に対面（全開講回数の過半数）、一部オンライン","isMedia":false},"eval":{"rows":[{"item":"期末試験","weight":100,"type":"exam"}]},"summary":"光情報は我々が見ている視覚情報であり，空間情報の取得に広く使われている．その他にも赤外や紫外をはじめとする様々な波長の情報や偏光情報を取得できる．こうした光情報を扱う基礎となる光学として，幾何光学と波動光学について概説する．幾何光学においては，カメラやレンズについて説明し，収差の取り扱いについて学ぶ．特に計算機を用いた光線追跡法のシミュレーションについて扱う．波動光学においては，フーリエ光学について解説し，回折計算とそのシミュレーションについて扱う．また社会における光学の応用である光工学について紹介する．特に3次元映像とホログラフィについて紹介し，計算機合成ホログラムの作成について扱う．","aims":"光情報工学の基礎となる幾何光学と波動光学について理解し，計算機を用いたシミュレーションができるようになること．また光工学の一例としてホログラフィを取り上げ，ホログラフィの基本的な原理を理解し，シミュレーションの実装ができるようになること．","goals":["幾何光学の基礎を理解し，光線行列について理解すること．","波動光学の基礎を理解し，回折計算の実装について理解すること．","光工学の実例であるホログラフィについて，そのシミュレーションについて理解すること．"],"plan":[{"n":1,"text":"Pythonの基礎（１）"},{"n":2,"text":"Pythonの基礎（２）"},{"n":3,"text":"幾何光学（１）"},{"n":4,"text":"幾何光学（２）"},{"n":5,"text":"幾何光学（３）"},{"n":6,"text":"幾何光学（４）"},{"n":7,"text":"波動光学（１）"},{"n":8,"text":"波動光学（２）"},{"n":9,"text":"波動光学（３）"},{"n":10,"text":"波動光学（４）"},{"n":11,"text":"波動光学（５）"},{"n":12,"text":"フーリエ光学（１）"},{"n":13,"text":"フーリエ光学（２）"},{"n":14,"text":"フーリエ光学（３）"},{"n":15,"text":"フーリエ光学（４）"}],"textbooks":"参考書 「Pythonで学ぶ光学の基礎」，谷田貝豊彦著，朝倉書店\n\"Introduction to Fourier Optics 4th edition\", Joseph W. Goodman, Macmillan Learning\n「高校数学でわかる光とレンズ 光の性質から、幾何光学、波動光学の核心まで」，竹内淳著，講談社\n「ホログラフィ入門 コンピュータを利用した3次元映像・3次元計測」，伊藤智義，下馬場朋禄著，講談社","prereq":"基礎的な線形代数や複素数に関する知識とプログラミングの経験．またフーリエ変換に習熟していることが望ましい．","prep":"プログラミング実習に関して，授業内で説明した内容の実装とレポート課題の作成","officeHour":[{"name":"塩見 日隆","day":"金曜日","time":"３限目，要予約","place":"理工学情報科学棟５F５０９室"}],"keywords":["幾何光学","光線追跡","波動光学","フーリエ光学","スカラー回折","ホログラフィ"],"teachers":["◎ 塩見 日隆"],"sdgs":["9"],"extra":[{"label":"区分1","text":"令和2年度以降入学生"},{"label":"区分2","text":"大学院科目"},{"label":"【テーマ（日本語）】(IN JAPANESE)","text":"幾何光学，波動光学の基礎からホログラフィのシミュレーションまで"},{"label":"【テーマ（英語）】(IN ENGLISH)","text":"From the foundation of geometric and wave optics to simulation of holography"},{"label":"授業形態","text":"講義形式が中心"},{"label":"教員の実務経験の有無","text":"無"}]}