{"cd":"1B807","lastUpdate":"20260312012237185","unit":"2.0","delivery":{"mode":"hybrid","raw":"主に対面（全開講回数の過半数）、一部オンライン","isMedia":false},"eval":{"rows":[{"item":"小レポート","weight":20,"type":"report"},{"item":"学習意欲・授業参加度","weight":40,"type":"attendance"},{"item":"中間レポート","weight":20,"type":"exam"},{"item":"期末レポート","weight":20,"type":"exam"}]},"summary":"沿岸の環境と生物資源の生態に関わる基礎的課題について、英文の文献を講読し，沿岸環境研究の背景や研究手法について理解を深める。演習IIIでは，受講学生は各自の研究に関連したテーマに沿って文献を検索し講読する論文を選定する。文献の内容をまとめて発表し，教員および履修学生で議論する。各学生は２本以上の関連文献を紹介し，最後にミニレビューとしてまとめ発表を行う。","aims":"沿岸環境と沿岸の生物の生態について，英文の文献を講読し，自らが行う研究の背景や研究手法について理解を深めるとともに，文献の内容をまとめ，発表する技術を身につける。","goals":["沿岸環境および沿岸の生物資源の生態関わる重要なテーマを選定できる。","テーマに沿って、既存の文献を検索し、重要な，また質の高い研究論文を選定できる。","あるテーマについての関連文献の内容を結びつけてまとめ，議論することができる。"],"plan":[{"n":1,"text":"テーマ設定と文献検索"},{"n":2,"text":"講読文献に関連する課題の解説"},{"n":3,"text":"論文の要約、紹介のための配布資料作成"},{"n":4,"text":"文献の要約、紹介のためのスライド資料作成"},{"n":5,"text":"文献紹介および討論"},{"n":6,"text":"発展的課題もしくは関連課題の文献検索"},{"n":7,"text":"科学論文の講読"},{"n":8,"text":"文献の要約、紹介のための配布資料作成"},{"n":9,"text":"文献の要約、紹介のためのスライド資料作成"},{"n":10,"text":"論文紹介および討論"},{"n":11,"text":"発展的課題もしくは関連課題の解説"},{"n":12,"text":"ミニレビュー構成の作成"},{"n":13,"text":"ミニレビューの作成"},{"n":14,"text":"ミニレビューの発表"},{"n":15,"text":"ミニレビュー執筆"},{"n":16,"text":"予備日"}],"textbooks":"検索して得た文献の他、必要に応じて、学術雑誌、研究教育機関等の参考記事を配布する。","prereq":"学士過程において、水圏環境や水生生物の生態学について学んでいること。沿岸環境学特論、沿岸環境学演習I, IIを履修していること。","prep":"各回の授業では、課題を出すので、次回の授業までに復習と予習を兼ねた授業時間外学習が必要になる。特に、履修学生自身の研究課題にも関連した文献の検索と関連知識の学習、ミニレビューの作成には十分な時間をかけて取り組むことが求められる。","officeHour":[{"name":"池島 耕","day":"火曜日","time":"3,4限","place":"沿岸環境学研究室(物部: II-1-13)"}],"keywords":["沿岸環境","生態","保全","文献講読","プレゼンテーション"],"teachers":["◎ 池島 耕"],"sdgs":["14"],"extra":[{"label":"英文科目名","text":"seminar on Coastal Ecology and Conservation III"},{"label":"区分1","text":"令和2年度以降入学生"},{"label":"区分2","text":"大学院科目"},{"label":"【テーマ（日本語）】(IN JAPANESE)","text":"沿岸環境と沿岸の生物の生態について英文の文献を講読し，自らが行う研究の背景や研究手法について理解を深める"},{"label":"関連科目名、関連科目コード番号\n【COMPUTER LINK / RELATED COURSES】","text":"「沿岸環境学特論」\n「沿岸環境学演習Ⅰ」\n「沿岸環境学演習Ⅱ」"},{"label":"成績評価に関する補足","text":"受講生が作成する配布資料とレポート(60%)，口頭発表と質疑応答(25%)、討論への参加内容(15%)で総合的に評価する。"},{"label":"オフィスアワーに関する補足","text":"事前にメールで予約すること。"},{"label":"授業形態","text":"口頭での質疑やディスカッションを含む"},{"label":"教員の実務経験の有無","text":"無"}]}