{"cd":"1F533","lastUpdate":"20260206091409489","unit":"4.0","delivery":{"mode":"onsite","raw":"対面のみ","isMedia":false},"eval":{"rows":[{"item":"学習意欲・授業参加度","weight":30,"type":"attendance"},{"item":"その他","weight":70,"type":"other"}]},"summary":"①「高知県内の地域課題」を題材にしたキャラクターを立案\n②「彫刻特論1」で修得した基礎知識を応用したフィギュア造形\n③「高知県内の地域課題」を題材にしたキャラクターのアニメーションのストーリーを考える\n④「彫刻特論Ⅱ」で修得したストップモーションを応用した効果的なアニメーション作成・動画配信","aims":"「高知県内の地域課題」を題材にしたキャラクターを立案し、「彫刻特論1」で修得した造形の基礎知識を応用することで、目的にあったフィギュア造形に取り組む。\n「高知県内の地域課題」を題材にしたキャラクターのアニメーションのストーリーを考え、「彫刻特論Ⅱ」で修得したストップモーションのアニメーション作成を応用することで、効果的なアニメーション作成・動画配信に取り組む。","goals":["「高知県内の地域課題」を題材にしたキャラクターを立案することができる。","「彫刻特論1」で修得した基礎知識を応用してフィギュア造形をすることができる。","「高知県内の地域課題」を題材にしたキャラクターのアニメーションのストーリーを考えることができる。","「彫刻特論Ⅱ」で修得したストップモーションを応用して、作成したフィギュアを活用した効果的なアニメーション作成・動画配信をすることができる。"],"plan":[{"n":1,"text":"「高知県内の地域課題」を考察"},{"n":2,"text":"「高知県内の地域課題」を題材にしたキャラクターの構想"},{"n":3,"text":"「高知県内の地域課題」を題材にしたキャラクターの立案"},{"n":4,"text":"「高知県内の地域課題」を題材にしたキャラクターのフィギュア作成1（芯材）"},{"n":5,"text":"「高知県内の地域課題」を題材にしたキャラクターのフィギュア作成2（スカルピー成形①）"},{"n":6,"text":"「高知県内の地域課題」を題材にしたキャラクターのフィギュア作成3（スカルピー成形②）"},{"n":7,"text":"「高知県内の地域課題」を題材にしたキャラクターのフィギュア作成4（スカルピー成形③）"},{"n":8,"text":"「高知県内の地域課題」を題材にしたキャラクターのフィギュア作成5（スカルピー成形④）"},{"n":9,"text":"「高知県内の地域課題」を題材にしたキャラクターのフィギュア作成6（スカルピー成形⑤）"},{"n":10,"text":"「高知県内の地域課題」を題材にしたキャラクターのフィギュア作成7（スカルピー成形⑥）"},{"n":11,"text":"「高知県内の地域課題」を題材にしたキャラクターのフィギュア作成8（着色①）"},{"n":12,"text":"「高知県内の地域課題」を題材にしたキャラクターのフィギュア作成9（着色②）"},{"n":13,"text":"「高知県内の地域課題」を題材にしたキャラクターのフィギュア作成10（プレゼンテーション）"},{"n":14,"text":"「高知県内の地域課題」を題材にしたキャラクターのアニメーションのストーリー作成1（シナリオ）"},{"n":15,"text":"「高知県内の地域課題」を題材にしたキャラクターのアニメーションのストーリー作成2（絵コンテ①）"},{"n":16,"text":"「高知県内の地域課題」を題材にしたキャラクターのアニメーションのストーリー作成3（絵コンテ②）"},{"n":17,"text":"「高知県内の地域課題」を題材にしたキャラクターのアニメーション作成1（セットの造形①）"},{"n":18,"text":"「高知県内の地域課題」を題材にしたキャラクターのアニメーション作成2（セットの造形②）"},{"n":19,"text":"「高知県内の地域課題」を題材にしたキャラクターのアニメーション作成3（セットの造形③）"},{"n":20,"text":"「高知県内の地域課題」を題材にしたキャラクターのアニメーション作成4（背景①）"},{"n":21,"text":"「高知県内の地域課題」を題材にしたキャラクターのアニメーション作成5（背景②）"},{"n":22,"text":"「高知県内の地域課題」を題材にしたキャラクターのアニメーション作成6（背景③）"},{"n":23,"text":"「高知県内の地域課題」を題材にしたキャラクターのアニメーション作成7（ストップモーション撮影①）"},{"n":24,"text":"「高知県内の地域課題」を題材にしたキャラクターのアニメーション作成8（ストップモーション撮影②）"},{"n":25,"text":"「高知県内の地域課題」を題材にしたキャラクターのアニメーション作成9（ストップモーション撮影③）"},{"n":26,"text":"「高知県内の地域課題」を題材にしたキャラクターのアニメーション作成10（ストップモーション撮影④）"},{"n":27,"text":"「高知県内の地域課題」を題材にしたキャラクターのアニメーション作成11（音響）"},{"n":28,"text":"「高知県内の地域課題」を題材にしたキャラクターのアニメーション作成12（MP4ファイル変換・動画配信）"},{"n":29,"text":"アニメーション動画配信の状況と効果の分析"},{"n":30,"text":"アニメーション動画配信の効果の検証\nまとめ"}],"textbooks":"適宜プリントを配布","prereq":"造形知識や応用実践能力の研鑽につとめること。","prep":"造形知識や応用実践能力の研鑽につとめること。","officeHour":[{"name":"阿部 鉄太郎","day":"金曜日","time":"５限（要予約）","place":"教育学部３号棟１階 阿部研究室"}],"keywords":["彫刻","彫刻特論Ⅰ・Ⅱ","サブカルチャー","フィギュア","アニメーション","ストップモーション","アニメーテッド・ラーニング","地域文化","地域産業","地域課題"],"teachers":["◎ 阿部 鉄太郎"],"extra":[{"label":"区分1","text":"令和6年度以降入学生"},{"label":"区分2","text":"大学院科目"},{"label":"履修に係わる注意事項\n【NOTES ON CLASS ENROLLMENT】","text":"「彫刻特論Ⅰ」「彫刻特論Ⅱ」を修得済であること。"},{"label":"成績評価に関する補足","text":"「その他」は立体造形作品・アニメーション作品。"},{"label":"授業形態","text":"口頭での質疑やディスカッションを含む"},{"label":"教員の実務経験の有無","text":"有\n教員の実務経験との関連\n中学校、高等学校で勤務経験のある教員が、その経験をいかして、芸術（美術）の基本的な知識と造形技法、地域芸術への向き合い方について講義する。"}]}