{"cd":"28036","lastUpdate":"20260219161326129","unit":"2.0","delivery":{"mode":"hybrid","raw":"主に対面（全開講回数の過半数）、一部オンライン","isMedia":false},"eval":{"rows":[{"item":"学習意欲・授業参加度","weight":75,"type":"attendance"},{"item":"期末試験","weight":25,"type":"exam"}]},"summary":"組織と人の管理、制度や運用について、その史的変遷、背景にある理論について学び、\n現代的な課題について考察する力をつける。","aims":"人事管理の理論を用いて、さまざまな事例について考察することで、人事管理論の基礎・応用について学ぶ。","goals":["人事管理の制度と運用についての基本的知識を習得し用語の意味が理解できる。","人事管理の理論と歴史的変遷および思想的背景が理解できる。","企業や組織における能力開発および管理に興味・関心をもつ。","現代における人事管理の課題および、解決のための施策･企業のケースについて理解できる。"],"plan":[{"n":1,"text":"オリエンテーション\n人事管理とは\n企業を取り巻く経営環境と人事管理"},{"n":2,"text":"人事管理の歴史的変遷（1） 科学的管理 フォードシステム\nテイラーの科学的管理、フォードシステムについて，人間を管理する手法の解説と，現代企業への応用を制度などの事例をあげて学ぶ。それらの管理における人間観のちがいを学習する。"},{"n":3,"text":"人事管理の歴史的変遷（2） 人間関係論\n人間関係論における人間を管理する手法の解説と，現代企業への応用を制度などの事例をあげて学ぶ。"},{"n":4,"text":"人事管理の歴史的変遷（3） 行動科学論\nマズロー, ハーズバーグ, マクレガーなどの行動科学論の諸理論について，順に解説していく。"},{"n":5,"text":"ティール組織の理論 心理的安全性の理論"},{"n":6,"text":"人事管理の制度（1）\n入り口と出口： 企業の採用活動から退職管理まで"},{"n":7,"text":"人事管理の制度（2）人材育成 －能力開発とキャリア形成－\n能力と能力開発について学習し、職場での多様な能力形成の方法を学ぶ。"},{"n":8,"text":"人事管理の制度（3）人事評価\n日本的経営の能力開発・人事考課・昇給･昇格・賃金管理を結びつける職能資格制度の概念を理解し、評価基準と評価誤差について学ぶ。"},{"n":9,"text":"人事管理の制度（4）配置・昇進・昇格の管理 リーダーシップ論\n企業内昇進・昇格、日本的な配置の考え方、リーダーシップについて学習する。"},{"n":10,"text":"賃金管理\n賃金の概念、賃金決定の方法と考え方、最近の状況について学習する。"},{"n":11,"text":"安全衛生管理 メンタルヘルス 過労死問題\n安全衛生管理の考え方"},{"n":12,"text":"労使関係管理\n日本的労使関係および労働組合について国際比較の中でその特徴およびメリット・デメリットを学習する。"},{"n":13,"text":"退職管理と定年制\n企業の出口としての退職について、解雇について、定年制、高齢者雇用について学ぶ。\n女性活躍推進"},{"n":14,"text":"人事管理の現代的課題： 「多様化」\n働き方改革 多様な働き方\n多様な労働者： 外国人労働者"},{"n":15,"text":"総括： これまでの授業の復習と補足"}],"textbooks":"教科書 必要に応じ、開講前に案内する","prereq":"「経営学概論」等でマネジメントの入門的な知識を得ていることが望ましいが必須ではない。","prep":"日常的に新聞・関連雑誌・参考文献等から関連情報に目を通すこと。\nとくに、独立行政法人労働研究・研修機構（ＪＩＬＰＴ）の『ビジネス・レーバー・トレンド』『日本労働研究雑誌』の授業に関連する記事を読むこと。（ＪＩＬＰＴ公式サイトでバックナンバーあるいは一部記事が公開されている）","officeHour":[{"name":"中川香代","day":"水曜","time":"５限","place":"人文棟１階東側 中川研究室 事前にメール等でアポイントを取るように"}],"keywords":["人事管理","人事労務管理","人的資源管理","マネジメント","企業","経営","管理"],"teachers":["◎ 中川 香代"],"sdgs":["8"],"extra":[{"label":"英文科目名","text":"Human Resource Management"},{"label":"区分1","text":"平成28年度以降入学生"},{"label":"区分2","text":"専門教育）専門科目"},{"label":"資格等","text":"教免－高校（商業）：商業の関係科目"},{"label":"関連科目名、関連科目コード番号\n【COMPUTER LINK / RELATED COURSES】","text":"「経営学概論」\n「経営管理論」"},{"label":"この授業で身につける「10+1の能力」","text":"専門分野に関する知識"},{"label":"Webテキスト\n【WEB TEXTBOOK / HOMEPAGE URL 】","text":"https://www.jil.go.jp/kokunai/blt/backnumber/2026/01_02/index.html"},{"label":"成績評価に関する補足","text":"「学習意欲・授業参加度」は、レスポンス・シートや課題等ではかります。"},{"label":"オフィスアワーに関する補足","text":"事前にメール等でアポイントを取るように。\n面談の日時と場所は相談の上、決定します。"},{"label":"教員の実務経験の有無","text":"無"},{"label":"授業形態","text":"講義形式が中心\n口頭での質疑やディスカッションを含む"}]}