{"cd":"52122","lastUpdate":"20260310154528370","unit":"1.0","delivery":{"mode":"onsite","raw":"対面のみ","isMedia":false},"eval":{"rows":[{"item":"小レポート","weight":20,"type":"report"},{"item":"学習意欲・授業参加度","weight":20,"type":"attendance"},{"item":"期末試験","weight":60,"type":"exam"}]},"summary":"看護倫理に基づいた倫理的判断ができるように学問的に学び、かつ自分の中の「徳」の部分を磨いていきます。","aims":"基礎看護学概論や生活援助論で学んだことを基本として、倫理的感受性を高めるための考え方を学ぶ。","goals":["医療の歴史から倫理観の変遷を理解できる","看護職にとって倫理綱領の必要性を説明できる","看護職に求められる倫理観について、自己の考えを述べることができる","看護実践で出会う倫理的課題の解決方法を検討することができる","実習に臨むための看護学生の倫理観を基本とした態度・行動について考えを述べることができる"],"plan":[{"n":1,"text":"10月8日 倫理が問われ始めた歴史的背景"},{"n":2,"text":"10月15日 看護者の倫理綱領、看護実践にとって重要な倫理原則"},{"n":3,"text":"10月22日 基盤となる倫理観と倫理的感受性"},{"n":4,"text":"10月29日 臨床で出会う身近な倫理問題"},{"n":5,"text":"11月12日 医療を受ける人々と健康との関連：臓器移植と臓器提供からいのちを考える"},{"n":6,"text":"11月19日 倫理問題を考える具体的な倫理分析（グループワーク）"},{"n":7,"text":"11月26日 倫理問題を考える具体的な倫理分析（発表）"},{"n":8,"text":"12月3日 看護学生の倫理について"},{"n":9,"text":"12月10日 定期試験"}],"textbooks":"【教科書】看護学概論 医学書院\n看護倫理 医学書院\n看護関係法令 医学書院\n※本授業では、医学書院のeテキストを使用しますので紙媒体の教科書を購入する必要はありません。\n【参考書】基礎看護学①看護学概論 メヂカルフレンド社\nナーシング・グラフィカ基礎看護学①看護学概論 メディカ出版\n臨床看護総論 医学書院","prereq":"テーマに対して思考することや関心を向けること、そして考えたことを表現すること。\nテーマに関連する内容の文献検討を深める。","prep":"授業テーマに沿って課題を実施する","officeHour":[{"name":"笹岡 晴香","day":"木曜日要予約","time":"12：00～13：00","place":"笹岡研究室"}],"keywords":["看護倫理","倫理綱領"],"teachers":["◎ 多田 邦子","笹岡 晴香"],"numbering":["42-22C2-11"],"sdgs":["3","17"],"extra":[{"label":"英文科目名","text":"Nursing Ethics"},{"label":"【テーマ（日本語）】(IN JAPANESE)","text":"看護実践の基盤となる看護倫理を学ぶ"},{"label":"関連科目名、関連科目コード番号\n【COMPUTER LINK / RELATED COURSES】","text":"「基礎看護学概論」\n「看護理論」"},{"label":"この授業で身につける「10+1の能力」","text":"専門分野に関する知識\n人類の文化・社会・自然に関する知識\n論理的思考力\n課題探求力\nコミュニケーション力\n協働実践力\n倫理観"},{"label":"履修に係わる注意事項\n【NOTES ON CLASS ENROLLMENT】","text":"授業資料は、授業3日前までにmoodle掲載します。\n授業までに各自で印刷もしくはダウンロードをして見れるようにしてください。"},{"label":"成績評価に関する補足","text":"学習意欲・授業参加度は、グループワーク・発表20％（各10点を2回）で評価する"},{"label":"オフィスアワーに関する補足","text":"事前にメールでアポイントメントを取ること"},{"label":"教員の実務経験の有無","text":"有\n教員の実務経験との関連\n病院等で看護師の勤務経験のある教員が、その経験を活かして、看護職の基本となる倫理綱領、看護に関する倫理的課題の解決方法などについて講義する"},{"label":"授業形態","text":"講義形式が中心\n口頭での質疑やディスカッションを含む\n授業中や授業時間外のグループワークを含む"}]}