{"cd":"60017","lastUpdate":"20260212103601995","unit":"2.0","delivery":{"mode":"onsite","raw":"対面のみ","isMedia":false},"eval":{"rows":[{"item":"学習意欲・授業参加度","weight":50,"type":"attendance"},{"item":"期末レポート","weight":50,"type":"exam"}]},"summary":"本科目の主な内容は次の2つです。\n(1) 社会調査データの分析で用いる主要な多変量解析の手法について、その基本的な考え方と主要な計量モデルを解説します。重回帰分析を基本としながら、学生の関心に応じて、三重クロス表分析、ロジスティック回帰分析、パス解析、因子分析、主成分分析等をとりあげます。\n(2) 実際の社会調査データと統計パッケージを用いて、受講生の関心に基づき、(1)で学んだ手法を実際に用いて行っていただきます。分析結果についてはレポート課題として提出を求めます。","aims":"社会調査データを入手して二次分析を行い、分析結果に基づくレポートを作成する。","goals":["自身の問題関心に応じた社会調査の公開データを探し出せるようになる","統計パッケージソフトを用いた調査データ分析ができるようになる","分析結果をレポート形式で報告できるようになる"],"plan":[{"n":1,"text":"イントロダクション・データ分析の準備(1)統計パッケージの入手"},{"n":2,"text":"データ分析の準備(2)公開調査データセットのダウンロードと利用準備"},{"n":3,"text":"社会統計学の復習"},{"n":4,"text":"多変量解析の手法(1)相関分析とその応用"},{"n":5,"text":"多変量解析の手法(2)エラボレーション（三重クロス表分析）"},{"n":6,"text":"多変量解析の手法(3)線形回帰分析の基本"},{"n":7,"text":"多変量解析の手法(4)線形回帰分析の応用"},{"n":8,"text":"多変量解析の手法(5)さらに高度な分析（上）\n※ 三重クロス表分析、ロジスティック回帰分析、パス解析、因子分析、主成分分析等から受講生の分析上の関心に基づき選択して解説する。"},{"n":9,"text":"多変量解析の手法(6)さらに高度な分析（下）\n※ 三重クロス表分析、ロジスティック回帰分析、パス解析、因子分析、主成分分析等から受講生の分析上の関心に基づき選択して解説する。"},{"n":10,"text":"多変量解析の実際(1)分析に向けた準備作業"},{"n":11,"text":"多変量解析の実際(2)変数の基礎的情報の確認"},{"n":12,"text":"多変量解析の実際(3)2変数の関連分析"},{"n":13,"text":"多変量解析の実際(4)多変量解析の実践"},{"n":14,"text":"多変量解析の実際(5)分析結果のとりまとめ"},{"n":15,"text":"多変量解析の実際(6)学期末レポート完成に向けて"},{"n":16,"text":"なし"}],"textbooks":"受講生の関心や必要を踏まえて決定します。","prereq":"以下の(1)から(3)全てにあてはまること。\n(1)「社会調査論」の単位を取得していること\n(2)「社会調査方法論」の単位を取得していること\n(3)「社会調査データ分析」または「統計解析の基礎」どちらかの単位を取得していること\n※社会調査士資格を取得するためには、上記の4科目全てに加えて、「質的調査法」か「多変量解析」のどちらかの履修・単位取得、さらに「社会調査実践演習」の履修・単位取得が必要です。詳細は一般社団法人社会調査協会ウェブサイトでご確認ください。","prep":"実際のデータを用いた分析や、結果の取りまとめを進めること。復習が非常に重要です。","officeHour":[{"name":"湊邦生","day":"火","time":"3限","place":"湊研究室ないしオンライン（どちらも要予約）"}],"keywords":["多変量解析","因果と相関","分散分析","回帰分析","統計パッケージ"],"teachers":["◎ 湊 邦生"],"numbering":["61-1118-11"],"sdgs":["4","11"],"extra":[{"label":"英文科目名","text":"Multi‐variable Analysis"},{"label":"地域関連科目","text":"地域関連科目"},{"label":"COC＋フェーズ","text":"2nd phase"},{"label":"【テーマ（日本語）】(IN JAPANESE)","text":"統計ソフトで多変量解析を使いこなす"},{"label":"【テーマ（英語）】(IN ENGLISH)","text":"Learn how to Conduct Multivariate Analyses with a Statistical Application"},{"label":"関連科目名、関連科目コード番号\n【COMPUTER LINK / RELATED COURSES】","text":"「統計解析の基礎」\n「社会調査データ分析」\n「社会調査論」"},{"label":"この授業で身につける「10+1の能力」","text":"論理的思考力\n課題探求力\n情報に関するリテラシー\n表現力"},{"label":"成績評価に関する補足","text":"15回の授業を通じて統計分析によるレポートを作成していきます。学習意欲・授業参加度はその過程について評価します。"},{"label":"教員の実務経験の有無","text":"無"},{"label":"授業形態","text":"口頭での質疑やディスカッションを含む"}]}