{"cd":"72122","lastUpdate":"20260521125401650","unit":"2.0","delivery":{"mode":"hybrid","raw":"主に対面（全開講回数の過半数）、一部オンライン","isMedia":false},"eval":{"rows":[{"item":"小テスト","weight":16,"type":"quiz"},{"item":"小レポート","weight":84,"type":"report"}]},"summary":"パソコン上でネットワークの検証環境を実際に構築しながら，実践的にネットワークプロトコルやネットワーク技術の知識を習得する。","aims":"演習を通じて，コンピュータネットワークのプロトコルや技術の理解を深める。","goals":["パケットキャプチャツール等を用いて通信内容を解析できるようになる","実際の動作を確認し，データリンク層(L2)，ネットワーク層(L3)，トランスポート層(L4)を理解する","L7の主要なプロトコル (HTTP, SSL/TLS, DNS, DHCP) を実践を通じて理解する"],"plan":[{"n":1,"text":"オリエンテーション，検証環境構築の準備（ツールの使い方の説明等）"},{"n":2,"text":"検証環境の構築"},{"n":3,"text":"データリンク層(1) Ethernet, ARP"},{"n":4,"text":"データリンク層(2) L2スイッチング, VLAN"},{"n":5,"text":"ネットワーク層(1) IP, ICMP"},{"n":6,"text":"ネットワーク層(2) ルーティング, NAT"},{"n":7,"text":"ネットワーク設計"},{"n":8,"text":"トランスポート層(1) UDP, TCP"},{"n":9,"text":"トランスポート層(2) UDPファイアウォール, TCPファイアウォール"},{"n":10,"text":"ソケットプログラミング"},{"n":11,"text":"HTTP, SSL/TLS"},{"n":12,"text":"DNS, DHCP"},{"n":13,"text":"サーバ負荷分散, SSLオフロード"},{"n":14,"text":"サーバ構築・設定"},{"n":15,"text":"これまでのまとめ，ペネトレーションテスト"}],"textbooks":"(教科書)[必携] 体験しながら学ぶネットワーク技術入門 (ISBN978-4-8156-1859-9)\n著者: みやたひろし\n出版社: SBクリエイティブ\n出版年: 2024年\n(参考書) 情報ネットワーク論で使用した教科書，参考書","prereq":"初歩的なUNIXコマンドが使えること。\n情報ネットワーク論を修得済みであることが望ましい。（情報ネットワーク論を修得済みであることを前提に授業を進めるため。）","prep":"課題に取り組むこと。","officeHour":[{"name":"三好 康夫","day":"火","time":"2限（要予約）","place":"理工学部情報科学棟 508"}],"keywords":["TCP/IP","VLAN","ルーティング","ファイアウォール","HTTPS"],"teachers":["◎ 三好 康夫","田所 亮"],"numbering":["33-3627-21"],"extra":[{"label":"英文科目名","text":"Exercises in Computer Networks"},{"label":"区分1","text":"平成29年度以降入学生"},{"label":"区分2","text":"専門教育）専門科目"},{"label":"【テーマ（日本語）】(IN JAPANESE)","text":"コンピュータネットワーク技術"},{"label":"【テーマ（英語）】(IN ENGLISH)","text":"Computer Network Technology"},{"label":"関連科目名、関連科目コード番号\n【COMPUTER LINK / RELATED COURSES】","text":"情報ネットワーク論"},{"label":"この授業で身につける「10+1の能力」","text":"専門分野に関する知識\n情報に関するリテラシー"},{"label":"履修に係わる注意事項\n【NOTES ON CLASS ENROLLMENT】","text":"情報科学棟計算機実習室の端末にアカウントが登録されていない人（情報科学科以外の学生）が受講する場合は，アカウントを登録する必要があるため，必ず事前に授業担当教員へ連絡すること。\n本授業は対面授業とするが，オンラインで実施する場合（7回以下）がある。"},{"label":"オフィスアワーに関する補足","text":"Teamsのチャットやメールなどで予約の連絡を入れること。"},{"label":"教員の実務経験の有無","text":"無"},{"label":"授業形態","text":"その他\n計算機実習室の端末を用いての演習が中心"}]}