{"cd":"72146","lastUpdate":"20260306111529463","unit":"2.0","delivery":{"mode":"hybrid","raw":"主に対面（全開講回数の過半数）、一部オンライン","isMedia":false},"eval":{"rows":[{"item":"小テスト","weight":30,"type":"quiz"},{"item":"小レポート","weight":20,"type":"report"},{"item":"期末試験","weight":50,"type":"exam"}]},"summary":"この授業では電気回路や電子回路を設計するために必要な考え方や設計スキルの理解を目指します。","aims":"我々の社会を支える情報システムはすべて電気エネルギーで動いています。電気エネルギーを利用するためには，電気回路や電子回路が必要です。本授業では電気工学概論を学び，実際のハードウェアの動作原理を理解するための基礎知識を身につけます。","goals":["電気回路に使われる電気抵抗，コンデンサー，コイルの役割を理解できる。","基本的な電気回路において，指定された条件を満足する抵抗値などが算出できる。","複素インピーダンスをもとにした有効電力，無効電力の考え方が理解できる。","演算増幅器を使った演算回路の基礎が理解できる。"],"plan":[{"n":1,"text":"ガイダンスと所有知識確認"},{"n":2,"text":"直流回路 (1) オームの法則，テブナンの定理などの諸法則"},{"n":3,"text":"直流回路 (2) キルヒホッフの法則"},{"n":4,"text":"直流回路 (3) 回路の諸量の計算演習"},{"n":5,"text":"交流回路 (1) 複素インピーダンスと瞬時値，実効値，平均値"},{"n":6,"text":"交流回路 (2) 交流回路の電力"},{"n":7,"text":"交流回路 (3) 直交表記した複素数の四則演算"},{"n":8,"text":"交流回路 (4) フェーザー表記した複素数の四則演算"},{"n":9,"text":"交流回路 (5) 回路の諸量の計算演習"},{"n":10,"text":"交流回路 (6) 三相交流回路"},{"n":11,"text":"電子回路 (1) 半導体の基礎"},{"n":12,"text":"電子回路 (2) pn接合応用素子"},{"n":13,"text":"電子回路 (3) 増幅回路"},{"n":14,"text":"電子回路 (4) 演算増幅回路"},{"n":15,"text":"電子回路 (5) 演算増幅回路の応用"}],"textbooks":"授業資料はMoodleを通じて配布します。参考書として電気電子工学に関する書籍を購入することを薦めます。","prereq":"記号式で連立方程式が解けること，複素数どうしの四則計算がおこなえることが望ましいが，本授業を通してそれらのスキルを身に付けたい人の参加も歓迎します。","prep":"授業で課す課題や試験の内容は電気回路の設計計算が主なものになります。これには，回路の各部で立式した記号式を連立方程式として解く数学スキルが必要です。課題を完成させるだけでなく，素早く確実に解を求めるための練習を繰り返し行なって下さい。","officeHour":[{"name":"芝 治也","day":"月曜日","time":"３時限以降（要事前予約）","place":"情報科学棟東館二階"}],"keywords":["電気回路設計","キルヒホッフの法則","インピーダンス","複素数","電子回路設計"],"teachers":["◎ 芝 治也"],"numbering":["33-2708-11","32-2623-11"],"sdgs":["7","9"],"extra":[{"label":"英文科目名","text":"Electrical Engineering"},{"label":"区分1","text":"平成29年度以降入学生"},{"label":"区分2","text":"専門教育）専門科目"},{"label":"【テーマ（日本語）】(IN JAPANESE)","text":"電気回路と電子回路の設計の基礎を学ぶ。"},{"label":"関連科目名、関連科目コード番号\n【COMPUTER LINK / RELATED COURSES】","text":"デジタル回路"},{"label":"この授業で身につける「10+1の能力」","text":"専門分野に関する知識\n論理的思考力"},{"label":"成績評価に関する補足","text":"講義への出席が10回に満たない履修生は合格としない。\n小レポート(課題含む）の提出期限遅れは，以下の観点で減点する。\n(1) 1週間以内の遅れは評価値X0.8\n(2) 1週間を超える遅れは0点。"},{"label":"オフィスアワーに関する補足","text":"moodleの授業ページに掲載する担当者メールアドレス宛に電子メールを送り，事前予約をして下さい。"},{"label":"教員の実務経験の有無","text":"有\n教員の実務経験との関連\n高等専門学校での教員経験30年以上の経験に基づき,ものづくりや企業等で求められる技術知識について解説する。\n南極地域観測隊での観測業務に1年間従事した経験に基づき，厳しい自然環境の中で生活や業務を継続する生活や計測のためのシステムについて語り，またチームワークの重要性について触れる。"},{"label":"授業形態","text":"講義形式が中心"}]}