{"cd":"74117","lastUpdate":"20260309094606801","unit":"2.0","delivery":{"mode":"hybrid","raw":"主にオンライン非同期型（全開講回数の過半数）、一部対面","isMedia":true},"eval":{"rows":[{"item":"小レポート","weight":30,"type":"report"},{"item":"期末試験","weight":70,"type":"exam"}]},"summary":"授業は，非同期型オンライン（moodle）で行う。一部の講義と試験は対面で行う。\n無機化学は周期表上の全ての元素の性質やそれらからなる多種多様な化合物を対象として扱う。無機化学Ⅰで学習した内容を基礎として，元素およびその化合物の性質を周期表に沿って系統的に理解するための基礎知識を深めることを主題とする。\n本講義では，多くの元素を取り扱うので，周期表に従って個々の元素の性質を系統的に学習することによって，元素の各論を理解できるようになることが重要である。具体的には，元素各論入門，水素の化学，1,2族元素の化学，13－18族元素の化学についての内容を取り扱う。","aims":"周期表に従って個々の元素の性質を系統的に学習することによって，元素の各論を理解できるようになることが重要である。具体的には，元素各論入門，水素の化学，1,2族元素の化学，13－18族元素の化学についての内容を学ぶ。","goals":["元素およびその化合物の性質を周期表に沿って系統的に理解するための基礎知識を身につける。","元素の各論を理解できるようになる。","水素の化学，1,2族元素の化学，13－18族元素の化学について理解し，説明できる。"],"plan":[{"n":1,"text":"授業内容の紹介，元素の特性を学ぶ意義"},{"n":2,"text":"元素各論入門① （原子の構造，分子の構造と結合）"},{"n":3,"text":"元素各論入門② （固体の構造，分子の対称性）"},{"n":4,"text":"水素の化学① （水素化合物の性質）"},{"n":5,"text":"水素の化学② （水素化合物の合成，反応）"},{"n":6,"text":"1族元素の化学① （1族元素およびその化合物の性質）"},{"n":7,"text":"1族元素の化学② （1族元素の化合物の安定性，溶解性）"},{"n":8,"text":"中間テスト\n2族元素の化学① （2族元素およびその化合物の性質）"},{"n":9,"text":"2族元素の化学② （2族元素の化合物の安定性，溶解性）"},{"n":10,"text":"13族元素の化学"},{"n":11,"text":"13，14族元素の化学"},{"n":12,"text":"14族元素の化学"},{"n":13,"text":"15族元素の化学"},{"n":14,"text":"15，16族元素の化学"},{"n":15,"text":"16族元素の化学"},{"n":16,"text":"期末試験"}],"textbooks":"教科書：「シュライバー無機化学（上）第６版」 田中他訳（東京化学同人）\n参考書：「化学 物質の構造,性質および反応」乾 利成，中原昭次，山内脩，吉川要三郎 （化学同人）\n「コットン・ウィルキンソン・ガウス基礎無機化学」 中原勝儼 訳 （培風館）\n「シュライバー無機化学（下）第６版」 田中他訳（東京化学同人）","prereq":"基礎無機化学，無機化学Ⅰを履修済みであること。","prep":"授業の復習を中心に，充分な時間外学習を行っていることを前提に講義を行います。\n毎週の課題プリントでは，その時間の重要ポイントが問題となっていますので，しっかりと取り組んでください。","officeHour":[{"name":"米村俊昭","day":"火","time":"12:00-13:00","place":"教員研究室（理工学部２号館２１７室）など"}],"keywords":["無機化学","典型元素","遷移金属元素","有機金属化学"],"teachers":["◎ 米村 俊昭"],"numbering":["35-3323-11"],"sdgs":["4","9","12"],"extra":[{"label":"英文科目名","text":"Inorganic Chemistry II"},{"label":"区分1","text":"平成29年度以降入学生"},{"label":"区分2","text":"専門教育）専門科目"},{"label":"資格等","text":"メディア授業科目"},{"label":"関連科目名、関連科目コード番号\n【COMPUTER LINK / RELATED COURSES】","text":"「無機化学I」\n「錯体化学」\n「無機化学演習」"},{"label":"この授業で身につける「10+1の能力」","text":"専門分野に関する知識\n人類の文化・社会・自然に関する知識\n論理的思考力\n課題探求力"},{"label":"成績評価に関する補足","text":"上記の期末試験(70%)には，中間テストの評価を含みます。"},{"label":"オフィスアワーに関する補足","text":"事前にメールなどで予約すれば，別の時間帯でも構いません。"},{"label":"教員の実務経験の有無","text":"無"},{"label":"授業形態","text":"講義形式が中心"}]}