{"cd":"77153","lastUpdate":"20260219172000365","unit":"8.0","delivery":{"mode":"onsite","raw":"対面のみ","isMedia":false},"eval":{"rows":[{"item":"その他","weight":100,"type":"other"}]},"summary":"配属された研究室で，卒業論文を作成する。研究目的の構築・理解，手法の意義，データ取得の注意点，得られたデータの整理・考察，論理的な結論，発表といった一連の作業を通して，研究の実践，指導を行い，卒業研究論文指導を行う。","aims":"３年次までに修得した知識とスキルを総合的に応用して地球環境や防災に関する研究を実施することにより，課題探求や問題解決能力の基盤となる力を身に付ける。","goals":["①先行研究の把握と課題・目的等の設定をすることができる。","②研究の目的達成のための調査・分析を適切に行うことができる。","③発表会での口頭発表において，発表および質疑応答を適切に行うことができる。","④自らの研究成果を(先行研究や参考文献の引用等も含め)筋道を立てて適切にまとめることができる。"],"plan":[{"n":1,"text":"配属された研究室で，卒業論文を作成する。研究目的の構築・理解，手法の意義，データ取得の注意点，得られたデータの整理・考察，論理的な結論，発表といった一連の作業を通して，研究の実践，指導を行い，卒業研究論文指導を行う。\n各教員の主な研究テーマ\n池原 実：南大洋の古海洋変動ダイナミクス，古黒潮学\n岩井雅夫：新生代の海洋環境ならびに低次海洋生物の多様性とその変遷\n大久保慎人：地震観測記録を用いた地震発生機構と地球内部構造の研究、地震学、地球物理学\n小原 涼太：メソスケール気象現象（cold-air damming、梅雨前線、竜巻等）に関する研究、高解像度の大気場データセットの開発と利活用\n加藤 悠爾：地質試料に産出する微化石（主に珪藻・黄金色藻シスト）を対象とした微古生物学分野の研究\n川畑 博：野外調査と岩石の観察・分析を通して、マグマの一生を読み解く研究\n坂本 淳：大規模災害時の道路ネットワーク復旧計画と被害軽減予測\n笹原克夫：降雨による斜面崩壊発生メカニズムの解明とその予測手法\n渋尾欣弘：①気候変動に伴う水災害ハザードの将来予測、②都市浸水予測技術の開発、③水害発生時における避難行動の意識調査\nZHANG XIN：気流の予測評価に有用とされる数値シミュレーションを用いて風の影響により発生する災害の予測\n藤内智士：野外調査を中心とした地殻変動に関する研究\n野口昌宏：中・大規模木造建築物や木質部材の開発、木造住宅の地震防災に関する研究\n橋本善孝：構造地質学・沈み込みプレート境界地震発生帯物質科学\n長谷川 精：野外調査と堆積学・地球化学分析から過去の地球の気候変動や惑星環境の復元\n原 忠：液状化などの地盤災害と地震防災・減災に関する工学的な研究\n松岡裕美：古地震の研究（海底活断層の研究、津波堆積物の研究）\n山田伸之：地震動（地盤や構造物の揺れ）および防災に資する・貢献するための研究\n村田文絵：バングラデシュに洪水をもたらす降水システムの研究、四国に大雨をもたらす降水システムの研究\n山本裕二：古地磁気学・岩石磁気学に基づく過去の地球磁場変動の解明\n第１回から第３０回までの間には以下のことなどを含めて指導を行う。具体的なスケジュールについては担当教員によって異なるので、必要に応じて担当教員に確認すること。\n・研究課題の設定\n・研究計画の立案\n・研究に取り組むための方法について\n・研究成果のまとめと、発表の準備"}],"textbooks":"担当教員が適宜指示します。","prereq":"卒業研究を行うのに必要な授業科目の単位（履修案内参照）．卒業研究に取り組むための情熱．","prep":"担当教員と相談の上，自ら積極的に関係分野の学習に努めること．","officeHour":[{"name":"担当教員により異なるので担当教員に問い合わせること。","day":"担当教員と調整すること","time":"担当教員と調整すること","place":"各教員の指示に従うこと。"}],"keywords":["地球科学","防災工学"],"teachers":["◎ 山田 伸之","小原 涼太","渋尾 欣弘","長谷川 精","松岡 裕美","岩井 雅夫","池原 実","橋本 善孝","村田 文絵","山本 裕二","藤内 智士","川畑 博","大久保 慎人","ZHANG XIN","笹原 克夫","野口 昌宏","坂本 淳","原 忠","加藤 悠爾","佐藤 哲郎"],"numbering":["36-4813-21"],"extra":[{"label":"英文科目名","text":"Graduation Research"},{"label":"区分1","text":"平成29年度以降入学生"},{"label":"区分2","text":"専門教育）専門科目"},{"label":"この授業で身につける「10+1の能力」","text":"専門分野に関する知識\n論理的思考力\n課題探求力\n表現力"},{"label":"履修に係わる注意事項\n【NOTES ON CLASS ENROLLMENT】","text":"※シラバスに記載されている内容や担当者は，変更される場合があります。"},{"label":"成績評価に関する補足","text":"授業に取り組む態度や取組みへの達成，発表会での状況などによって評価(100%)する。評価方法はルーブリックに基づく。最終成績を学科会議で検討する。"},{"label":"オフィスアワーに関する補足","text":"各教員の指示があります。"},{"label":"教員の実務経験の有無","text":"無"},{"label":"授業形態","text":"授業中や授業時間外のグループワークを含む"}]}