{"cd":"86066","lastUpdate":"20260309230043330","unit":"6.0","delivery":{"mode":"onsite","raw":"対面のみ","isMedia":false},"summary":"イネ品種の作物生理、熱帯有用作物の栽培生理、環境保全型農業、環境ストレス耐性","aims":"科学論文の作成、専門の知識・技術の習得を通して、計画性、情報収集力、確実性、洞察力、説明能力、情報整理能力、論理性の各技能を身につける。また、作業を通して、積極性、協調性を身につけ、時間感覚を磨く。","goals":["みとおす：結論の仮説をたて、結果を予測し、実行に移すための計画スケジュールをたてることができる（計画性）","卒論に関する文献を自ら収集しまとめることができる（情報収集能力）","たしかめる：情報に間違いがないか確認することができる（確実性）","きく：相手が聞きたいことの本質を見抜くことができる、情報を総合し妥当な推察を導くことができる（洞察力）","はなす：わかりやすく説明することができる、概要を説明することができる（説明能力）","データを正確に入力・計算・解析することができる（情報整理能力）","かく：文章を仕分け、筋道をたてて結論に導くことができる（論理性）"],"plan":[{"n":1,"text":"計画発表会"},{"n":2,"text":"栽培・調査"},{"n":3,"text":"分析・データ解析"},{"n":4,"text":"四国支部講演会・中間発表"},{"n":5,"text":"要旨提出・本文完成\n発表会"}],"textbooks":"イネの生長・星川清親著・農山漁村文化協会\n作物学用語集・日本作物学会編・養賢堂\n農学基礎セミナー 作物栽培の基礎・堀江武編著・農山漁村文化協会","prereq":"１）コアタイムは月～金曜日の8:50-17:00であるので、この時間は研究室に在室し、実験、勉学に励むこと。\n２）卒論は通年科目であるため基本的に学期間休みはない。栽培実験では休み期間中も測定や管理をおこなう必要がある。\n３）就職活動、授業は優先させてよいが、その次には卒論を優先させ、アルバイトや旅行を優先させない。\n４）作業、測定、サンプリングは一人では困難であるので基本的に共同でおこなう。協力し合い、相互に連絡を密にし、特に自分の研究を手伝ってもらうときは連絡ミスがないように注意すること。\n５）研究室は勉強する場所であるので、娯楽物（マンガ、ゲームなど）を持ち込まない。特に大型の物品を持ち込まない。","prep":"文献検索の方法を指導するので関連文献を収集する。参考図書を熟読する。教員の指導を受けながら実験計画発表会、中間発表、卒業論文発表会の準備を遅延なく進める。","officeHour":[{"name":"宮崎彰","day":"水曜","time":"12:00-13:00","place":"作物教員研究室（要予約）"}],"keywords":["実験・実習","栽培","調査・分析","計画","データまとめ","作物学","植物学","土壌学","遺伝学","環境保全農業論"],"teachers":["◎ 宮崎 彰"],"sdgs":["1","2","9","13"],"extra":[{"label":"英文科目名","text":"Graduation Thesis"},{"label":"区分1","text":"平成28年度以降入学生／平成27年度以前入学生"},{"label":"区分2","text":"専門教育）専門科目／専門科目"},{"label":"関連科目名、関連科目コード番号\n【COMPUTER LINK / RELATED COURSES】","text":"「暖地農学概論」\n「作物学」"},{"label":"この授業で身につける「10+1の能力」","text":"専門分野に関する知識\n人類の文化・社会・自然に関する知識\n論理的思考力\n課題探求力\n語学に関するリテラシー\n情報に関するリテラシー\n表現力\nコミュニケーション力\n協働実践力\n自律力\n倫理観\n統合・働きかけ"},{"label":"履修に係わる注意事項\n【NOTES ON CLASS ENROLLMENT】","text":"定員4名"},{"label":"成績評価に関する補足","text":"栽培管理、報告・相談の状況、取り組み姿勢：チェックリストを月ごとに評価し平均（100点）。\n総合評価：実験の達成度（計画の量に対して）およびルーブリック（成績評価基準）を加味する。"},{"label":"教員の実務経験の有無","text":"有\n教員の実務経験との関連\n作物の栽培調査研究の実務経験を有する教員が、計画、栽培、データ取りまとめ、解析、論文作成を指導する。"},{"label":"授業形態","text":"口頭での質疑やディスカッションを含む\n授業中や授業時間外のグループワークを含む"}]}