{"cd":"86097","lastUpdate":"20260619165429996","unit":"6.0","delivery":{"mode":"onsite","raw":"対面のみ","isMedia":false},"eval":{"rows":[{"item":"小レポート","weight":20,"type":"minireport"},{"item":"中間レポート","weight":40,"type":"report"},{"item":"期末レポート","weight":40,"type":"report"}]},"summary":"自身の設定したテーマに関して、情報収集・整理・分析により得られたデータをもとに論文執筆と成果発表を行う。授業内では論文執筆と成果発表に必要な知識と技術を身につけていく。","aims":"自身の設定したテーマに関して、研究計画を立て、適切に実行（情報収集・整理・分析）する能力を身につける。調査研究から得られた結論を論理的に整理し、適切な方法（文書・資料として）で、他者に伝達できる能力を養う。","goals":["卒業論文のテーマに基づく既存文献の収集・整理ができる。","卒業論文のテーマに従い、研究計画・調査計画の策定を策定し、遂行できる。","得られた情報を適切に管理し、分析できる。","分析結果を論理的に整理できる。","研究成果をもとに論文を執筆する。学術論文の執筆手法を身につけると共に文章作成を通じて論理的思考を向上させる。","研究成果をもとにした成果発表を行う。プレゼン資料の作成方法、発表内容の構成などを含む発表技術を向上させる。"],"plan":[{"n":1,"text":"〈研究計画立案、進捗状況報告〉\n研究を行う上で、課題の背景と自らの研究課題の目的を理解し、関連分野の論文を読むことで研究計画を立案する。\n調査研究実施によって得られた結果について、進捗状況報告を行う"},{"n":2,"text":"〈調査研究の実施〉\n食料農業市場学の研究を行う。設定した課題を明らかにするために調査手法・調査先を選定し、実施する。教員の指導に加えて自ら主体的に研究計画に沿って研究活動を進める。"},{"n":3,"text":"〈論文執筆と発表資料の作成〉\n研究結果を適切に解釈し、まとめる。研究に用いた資料等から内容を理解し、文章化して説明できるようにする。それらの内容をもとに発表資料を簡潔にまとめる。"}],"textbooks":"日本農業市場学会（編）（2019）『農産物・食品の市場と流通』筑波書房","prereq":"事実と解釈を分けて、わかりやすくまとめ、結果をもとにした議論を行い日々の研究活動に反映する。","prep":"文献研究、調査研究の準備・実施・結果をまとめる、合同ゼミ、論文作成を各自で行う。","officeHour":[{"name":"脇谷祐子","day":"土日を除く 要予約","time":"土日を除く 要予約","place":"研究室"}],"keywords":["卒業論文","農業経済学","食料農業市場学"],"teachers":["◎ 脇谷 祐子"],"extra":[{"label":"英文科目名","text":"Graduation Thesis"},{"label":"区分1","text":"平成28年度以降入学生／平成27年度以前入学生"},{"label":"区分2","text":"専門教育）専門科目／専門科目"},{"label":"この授業で身につける「10+1の能力」","text":"専門分野に関する知識\n人類の文化・社会・自然に関する知識\n論理的思考力\n課題探求力\n語学に関するリテラシー\n情報に関するリテラシー\n表現力\nコミュニケーション力\n協働実践力\n自律力\n倫理観\n統合・働きかけ"},{"label":"成績評価に関する補足","text":"小レポート：研究計画の発表内容\n中間レポート：研究進捗状況の発表内容、合同ゼミの発表内容\n期末レポート：卒業論文の執筆内容と卒業論文発表会での発表内容、それらに対する取り組み状況"},{"label":"教員の実務経験の有無","text":"無"},{"label":"授業形態","text":"口頭での質疑やディスカッションを含む"}]}