{"cd":"86447","lastUpdate":"20260216232844429","unit":"1.0","delivery":{"mode":"onsite","raw":"対面のみ","isMedia":false},"summary":"卒業論文演習Ⅱでは、卒業論文研究に関連した魚類生態の論文の精読・発表を通してその専門知識を深めることを目標とする。 また、他の受講生の発表から魚類研究に関連する知識を広めるとともに、演習内での質疑応答を通して科学的・論理的思考に基づいた意見交換ができるような能力を身につける。全体で5部構成となっており，各部では目的別に3段階に分かれている。","aims":"１．卒業論文研究に関する研究分野の専門知識を身につける。\n２．自らの専門分野に対する質問に対して的確に答える能力を身につける。","goals":["卒業論文研究に関する研究分野の専門知識を身につけることができる。","自らの専門分野に対する質問に対して的確に答える能力を身につけることができる。"],"plan":[{"n":1,"text":"卒業論文の研究内容に関連する科学論文の収集と発表論文の選定。第一部1回目はキーワード検索による文献のリスト化を行う。"},{"n":2,"text":"卒業論文の研究内容に関連する科学論文の収集と発表論文の選定。第一部2回目は要旨の内容から自身の研究に関連する論文をいくつか選定する。"},{"n":3,"text":"卒業論文の研究内容に関連する科学論文の収集と発表論文の選定。第一部3回目は，第2回目で選定した論文から，自身の研究に大きく貢献する内容の論文を決定する。"},{"n":4,"text":"選定した科学論文の内容の整理と要約の作成。第二部1回目は緒言と方法の要点をまとめる。"},{"n":5,"text":"選定した科学論文の内容の整理と要約の作成。第二部2回目は結果と考察の要点をまとめる。"},{"n":6,"text":"選定した科学論文の内容の整理と要約の作成。第二部3回目は，緒言から考察までの要点を論理的な構成を意識しながら文章としてまとめて要旨にする。"},{"n":7,"text":"選定した論文の実験計画法や解析手法の問題点や課題についての紹介。第三部1回目は論文の実験計画の優れた点をその理由とともに発表する。"},{"n":8,"text":"選定した論文の実験計画法や解析手法の問題点や課題についての紹介。第三部２回目は論文の実験計画の欠点をその理由とともに発表する。"},{"n":9,"text":"選定した論文の実験計画法や解析手法の問題点や課題についての紹介。第三部3回目は論文の統計解析の妥当性をその理由とともに発表する。"},{"n":10,"text":"科学論文での研究結果の示し方（図表）の紹介と実践。第四部1回目はグラフの種類とデータの示し方について学び，発表する。"},{"n":11,"text":"科学論文での研究結果の示し方（図表）の紹介と実践。第四部２回目は表とデータの示し方について学ぶ。"},{"n":12,"text":"科学論文での研究結果の示し方（図表）の紹介と実践。第四部３回目は論文と発表スライドでの図表の示し方の違いについて調べて発表する。"},{"n":13,"text":"卒業論文に関連する科学論文の内容の紹介と質疑。第五部１回目は，結果と考察のつなぎ方を意識した発表を行う。"},{"n":14,"text":"卒業論文に関連する科学論文の内容の紹介と質疑。第五部２回目は，その研究で得られた結論の妥当性について発表する。"},{"n":15,"text":"卒業論文に関連する科学論文の内容の紹介と質疑。第五部３回目は，その研究から得られた成果から研究課題の発展における今後の展望について発表する。"}],"textbooks":"魚類生態学の基礎 塚本勝巳編 恒星社厚生閣\n魚類学 矢部・桑村・都木 編 恒星社厚生閣","prereq":"魚類学概論や水産生物学を履修していることが望ましい。あるいはそれと同等の知識を有すること。","prep":"関連分野の予習と復習","officeHour":[{"name":"中村洋平","day":"木曜日","time":"4限","place":"物部4号棟西棟２F西端"}],"keywords":["魚類","生態","海洋"],"teachers":["◎ 中村 洋平"],"extra":[{"label":"英文科目名","text":"Graduation Thesis Seminar"},{"label":"区分1","text":"平成28年度以降入学生／平成27年度以前入学生"},{"label":"区分2","text":"専門教育）専門科目／専門科目"},{"label":"【テーマ（日本語）】(IN JAPANESE)","text":"魚類生態の知識を深め，伝える"},{"label":"この授業で身につける「10+1の能力」","text":"専門分野に関する知識\n論理的思考力\n表現力"},{"label":"成績評価に関する補足","text":"(1)授業への参加態度 30%\n(2)プレゼンテーションと作成資料の出来栄え 50%\n(3)ディスカッションへの貢献度 20%"},{"label":"教員の実務経験の有無","text":"無"}]}